[{"slug":"kujoyu","city":"kyoto","title":" Sento / Kujoyu","description":"https://www.japantimes.co.jp/life/2016/11/05/lifestyle/washed-tokyos-iconic-communal-bath-houses-face-uncertain-future/ Kujoyu 昭和の銭湯、レンタルスペースに改装 京都・九条湯印刷用画面を開く １０年前に廃業した銭湯を改装したレンタルスペース。９月のプレオープンイベントではボードゲーム大会が開かれた（京都市南区東九条中御霊町...","url":"/kyoto/kujoyu","public":false,"date":"3/27/2019","category":"place","mapPosition":[{"location":"Kujoyu","bearing":0,"center":[135.762486,34.978067],"zoom":12,"pitch":0}],"image":"/posts/kyoto/kujoyu/med/kujoyu1.jpg","languages":{"en":true,"ja":false}},{"slug":"introduction","city":"kyoto","title":" Urbanist's guide to Kyoto","description":"• Chidori Bunka by dot architects • Creative Center OSAKA is a renoveted shipyard that is now used to support the creative activities in Osaka. This buildings is resistered as a cultural heritage site...","url":"/kyoto/introduction","public":false,"date":"6/26/2018","category":"intro","mapPosition":[{"location":"Chidori Bunka","bearing":0,"center":[135.475075,34.621664],"zoom":12,"pitch":0},{"location":"","bearing":0,"center":[-118.2464493,33.9900691],"zoom":12,"pitch":0},{"location":"","bearing":0,"center":[-118.23744390000002,34.0454001],"zoom":12,"pitch":0},{"location":"","bearing":0,"center":[-118.23487999999998,34.046146],"zoom":12,"pitch":0},{"location":"","bearing":0,"center":[-118.23640720000003,34.0445952],"zoom":12,"pitch":0},{"location":"","bearing":0,"center":[-118.23289219999998,34.0450119],"zoom":12,"pitch":0},{"location":"","bearing":0,"center":[-118.29440799999998,34.0999515],"zoom":12,"pitch":0},{"location":"","bearing":0,"center":[-118.29278959999999,34.1161926],"zoom":12,"pitch":0},{"location":"","bearing":0,"center":[-118.2480433,34.0434704],"zoom":12,"pitch":0}],"image":"","languages":{"en":true,"ja":false}},{"slug":"realestate","city":"kyoto","title":" Urbanist's guide to Kyoto","description":"・中央卸売市場界隈 株式会社めい ・島原界隈 itonowa を中心に個人事業主の集まり ・五条楽園界隈 株式会社ハチセ ・崇仁地区 崇仁新町って場所を運営している団体わからず、どこかの株式会社かと思うのですが、面識ないです ・東九条 ・新大宮商店街 ・堀川団地 フラットエージェンシー ","url":"/kyoto/realestate","public":false,"date":"6/26/2018","category":"intro","mapPosition":[{"location":"Chidori Bunka","bearing":0,"center":[135.475075,34.621664],"zoom":12,"pitch":0},{"location":"","bearing":0,"center":[-118.2464493,33.9900691],"zoom":12,"pitch":0},{"location":"","bearing":0,"center":[-118.23744390000002,34.0454001],"zoom":12,"pitch":0},{"location":"","bearing":0,"center":[-118.23487999999998,34.046146],"zoom":12,"pitch":0},{"location":"","bearing":0,"center":[-118.23640720000003,34.0445952],"zoom":12,"pitch":0},{"location":"","bearing":0,"center":[-118.23289219999998,34.0450119],"zoom":12,"pitch":0},{"location":"","bearing":0,"center":[-118.29440799999998,34.0999515],"zoom":12,"pitch":0},{"location":"","bearing":0,"center":[-118.29278959999999,34.1161926],"zoom":12,"pitch":0},{"location":"","bearing":0,"center":[-118.2480433,34.0434704],"zoom":12,"pitch":0}],"image":"","languages":{"en":true,"ja":false}}]